{"title":"Megan - RSL Meet Scores [Final]","values":[["Jun 18,2025","Fawn Lake at Massad YMCA","Unknown",560.0,"Fawn Lake",457.0,"Unknown"],["Jun 18,2025","Curtis Park at Woodlands","Woodlands",674.0,"Unknown",366.0,"Woodlands"],["Jun 18,2025","Curtis Park at Woodlands","Unknown",674.0,"Curtis Park",366.0,"Unknown"],["Jun 18,2025","Caroline at Fredericksburg CC","Unknown",554.0,"Unknown",325.0,"Unknown"],["Jun 18,2025","Idlewild at Eden Estates","Eden Estates",564.0,"Unknown",341.0,"Eden Estates"],["Jun 18,2025","Caroline at Fredericksburg CC","Fredericksburg CC",554.0,"Unknown",325.0,"Fredericksburg CC"],["Jun 18,2025","Spotswood at Hampton Oaks","Hampton Oaks",492.0,"Unknown",508.0,"Unknown"],["Jun 18,2025","Lee's Hill at Lake of the Woods","Unknown",515.0,"Lee's Hill",454.0,"Unknown"],["Jun 18,2025","Lake Wilderness at Salem Fields","Salem Fields",559.0,"Unknown",422.0,"Salem Fields"],["Jun 18,2025","Chancellor at Ferry Farm","Unknown",533.0,"Chancellor",462.0,"Unknown"],["Jun 18,2025","Fox Point at Dahlgren","Unknown",348.0,"Fox Point",662.0,"Fox Point"],["Jun 18,2025","Grafton at College Heights","Unknown",469.5,"Grafton",517.5,"Grafton"],["Jun 18,2025","Idlewild at Eden Estates","Unknown",564.0,"Idlewild",341.0,"Unknown"],["Jun 18,2025","Leeland Station at Austin Ridge","Unknown",486.5,"Leeland Station",542.5,"Leeland Station"],["Jun 18,2025","Lee's Hill at Lake of the Woods","Lake of the Woods",515.0,"Unknown",454.0,"Lake of the Woods"],["Jun 18,2025","Spotswood at Hampton Oaks","Unknown",492.0,"Spotswood",508.0,"Spotswood"],["Jun 18,2025","Fox Point at Dahlgren","Dahlgren",348.0,"Unknown",662.0,"Unknown"],["Jun 18,2025","Lake Wilderness at Salem Fields","Unknown",559.0,"Lake Wilderness",422.0,"Unknown"],["Jun 18,2025","Chancellor at Ferry Farm","Ferry Farm",533.0,"Unknown",462.0,"Ferry Farm"],["Jun 18,2025","Leeland Station at Austin Ridge","Austin Ridge",486.5,"Unknown",542.5,"Unknown"],["Jun 18,2025","Grafton at College Heights","College Heights",469.5,"Unknown",517.5,"Unknown"],["Jun 18,2025","Hopyard at Spotsy Y","Spotsy Y",459.0,"Unknown",511.0,"Unknown"],["Jun 18,2025","Hopyard at Spotsy Y","Unknown",459.0,"Hopyard",511.0,"Hopyard"],["Jun 18,2025","Fawn Lake at Massad YMCA","Massad YMCA",560.0,"Unknown",457.0,"Massad YMCA"]],"fields":["Meet Date","Meet Name","Home Team","Home Score","Away Team","Away Score","Winner"],"types":[25,25,25,701,25,701,25],"type_names":["text","text","text","float","text","float","text"],"started_at":"2025-06-27 17:44:38 +0000","finished_at":"2025-06-27 17:46:17 +0000","checksum":"804512782b22e49c6c9c6f2e2400df2f"}
